netbox_kafka_consumer/__init__.py
netbox_kafka_consumer-1.0.16.dist-info/LICENSE
netbox_kafka_consumer-1.0.16.dist-info/METADATA
netbox_kafka_consumer-1.0.16.dist-info/WHEEL
netbox_kafka_consumer-1.0.16.dist-info/top_level.txt
netbox_kafka_consumer-1.0.16.dist-info/RECORD
