Metadata-Version: 2.1
Name: netbox-kafka-consumer
Version: 1.0.16
Summary: Easily consume NetBox changes from Kafka
Home-page: https://github.com/ebusto/netbox-kafka-consumer
Author: Eric Busto
Author-email: ebusto@nvidia.com
License: UNKNOWN
Platform: UNKNOWN
Classifier: License :: OSI Approved :: MIT License
Classifier: Operating System :: OS Independent
Classifier: Programming Language :: Python :: 3
License-File: LICENSE
Requires-Dist: confluent-kafka (==1.5.0)
Requires-Dist: funcsigs (==1.0.2)
Requires-Dist: future (==0.18.2)
Requires-Dist: pynetbox (==6.6.2)
